setup.py
VoiceBot/Bot.py
VoiceBot/BotServer.py
VoiceBot/CallCenter.py
VoiceBot/Esl_AsrDemo.py
VoiceBot/InboundDemo.py
VoiceBot/SampleBot.py
VoiceBot/__init__.py
VoiceBot.egg-info/PKG-INFO
VoiceBot.egg-info/SOURCES.txt
VoiceBot.egg-info/dependency_links.txt
VoiceBot.egg-info/top_level.txt
VoiceBot/AutoCall/AutoDialer.py
VoiceBot/AutoCall/Dialer.py
VoiceBot/AutoCall/__init__.py
VoiceBot/MyDialog/__init__.py
VoiceBot/MyDialog/d_payback.py
ai_bot/__init__.py
callcenter/__init__.py